LICENSE
Markdown_to_HTML.py
PDF.md
README.md
images_to_video.py
media_editing.py
setup.py
shrinkpdf.sh
text_to_QR_code.py
vidgif.py
media/Audio_Recorder.png
media_editing.egg-info/PKG-INFO
media_editing.egg-info/SOURCES.txt
media_editing.egg-info/dependency_links.txt
media_editing.egg-info/entry_points.txt
media_editing.egg-info/requires.txt
media_editing.egg-info/top_level.txt
setup/Audacity/MultiVoiceChorus.ny
setup/Inkscape/colours_1.gpl
setup/audio-recorder/audio-recorder_1.6-3-vivid_amd64.deb
setup/audio-recorder/audio-recorder_1.7-5~xenial_amd64.deb