Metadata-Version: 1.0
Name: media-editing
Version: 2021.10.17.2018
Summary: media editing
Home-page: https://github.com/wdbm/media_editing
Author: Will Breaden Madden
Author-email: wbm@protonmail.ch
License: GPLv3
Platform: UNKNOWN
